geometrylib/__init__.py
geometrylib/shapes2d.py
geometrylib/shapes3d.py
geometrylib/utils.py
razicube-0.1.0.dist-info/METADATA
razicube-0.1.0.dist-info/WHEEL
razicube-0.1.0.dist-info/top_level.txt
razicube-0.1.0.dist-info/RECORD
