Metadata-Version: 2.4
Name: razicube
Version: 0.1.0
Summary: مكتبة شاملة لحساب المساحة والمحيط للأشكال الثنائية والثلاثية الأبعاد
Home-page: 
Author: Razi Ramzi
Classifier: Programming Language :: Python :: 3
Classifier: License :: OSI Approved :: MIT License
Classifier: Operating System :: OS Independent
Dynamic: author
Dynamic: classifier
Dynamic: description
Dynamic: description-content-type
Dynamic: summary
